{
	"singer": "姫诗鹤", 
	"detail": "几乎华语only选手+低音苦手，概率开启高音鸟叫模式（bushi）（目前无试听）",
    "url": "singer?singer=zhensh",
    "audio": "../audios/zhensh.mp3",
	"songs": [
        {"title": "天光", "artist": ""},
        {"title": "孤帆", "artist": ""},
        {"title": "春逝", "artist": ""},
        {"title": "来客", "artist": ""},
        {"title": "夜昙", "artist": ""},
        {"title": "万梦星", "artist": ""},
        {"title": "云何住", "artist": ""},
        {"title": "不老梦", "artist": ""},
        {"title": "山月记", "artist": ""},
        {"title": "南关醉", "artist": ""},
        {"title": "雁去台", "artist": ""},
        {"title": "愚人歌", "artist": ""},
        {"title": "歌乐天", "artist": ""},
        {"title": "洛维娜", "artist": ""},
        {"title": "楚歌起", "artist": ""},
        {"title": "四万秋", "artist": ""},
        {"title": "西江月·世事一场大梦", "artist": ""},
        {"title": "Landing Guy", "artist": ""},
        {"title": "罚酒饮得", "artist": ""},
        {"title": "天地缓缓", "artist": ""},
        {"title": "一梦惊鸿", "artist": ""},
        {"title": "海之礼赞", "artist": ""},
        {"title": "痴梦李贺", "artist": ""},
        {"title": "红拂夜奔", "artist": ""},
        {"title": "敢归云间宿", "artist": ""},
        {"title": "去追一只鹿", "artist": ""},
        {"title": "于荒径之中", "artist": ""},
        {"title": "忘川风华录系列", "artist": ""},
        {"title": "何日重到苏澜桥", "artist": ""}
    ]}
